qtrf/__init__.py
qtrf/qtrf.py
qtrf/units.py
qtrf/mixins/__init__.py
qtrf/mixins/line_edit.py
qtrf/mixins/value.py
qtrf/widgets/__init__.py
qtrf/widgets/amps/__init__.py
qtrf/widgets/amps/label.py
qtrf/widgets/amps/line_edit.py
qtrf/widgets/celsius/__init__.py
qtrf/widgets/celsius/label.py
qtrf/widgets/celsius/line_edit.py
qtrf/widgets/db/__init__.py
qtrf/widgets/db/label.py
qtrf/widgets/db/line_edit.py
qtrf/widgets/dbm/__init__.py
qtrf/widgets/dbm/label.py
qtrf/widgets/dbm/line_edit.py
qtrf/widgets/file/__init__.py
qtrf/widgets/file/ui_filewidget.py
qtrf/widgets/file/widget.py
qtrf/widgets/hz/__init__.py
qtrf/widgets/hz/label.py
qtrf/widgets/hz/line_edit.py
qtrf/widgets/ip_address/__init__.py
qtrf/widgets/ip_address/line_edit.py
qtrf/widgets/meters/__init__.py
qtrf/widgets/meters/label.py
qtrf/widgets/meters/line_edit.py
qtrf/widgets/ohms/__init__.py
qtrf/widgets/ohms/label.py
qtrf/widgets/ohms/line_edit.py
qtrf/widgets/ports/__init__.py
qtrf/widgets/ports/label.py
qtrf/widgets/ports/line_edit.py
qtrf/widgets/ports/ports.py
qtrf/widgets/ports/mixin/__init__.py
qtrf/widgets/ports/mixin/focus.py
qtrf/widgets/ports/mixin/list.py
qtrf/widgets/ports/mixin/validator.py
qtrf/widgets/touchstone/__init__.py
qtrf/widgets/touchstone/widget.py
qtrf/widgets/user_corrections/__init__.py
qtrf/widgets/user_corrections/widget.py
qtrf/widgets/value/__init__.py
qtrf/widgets/value/label.py
qtrf/widgets/value/line_edit.py
qtrf/widgets/volts/__init__.py
qtrf/widgets/volts/label.py
qtrf/widgets/volts/line_edit.py
qtrf-1.8.3.dist-info/METADATA
qtrf-1.8.3.dist-info/WHEEL
qtrf-1.8.3.dist-info/entry_points.txt
qtrf-1.8.3.dist-info/top_level.txt
qtrf-1.8.3.dist-info/RECORD
