Metadata-Version: 2.1
Name: qtrf
Version: 1.8.3
Summary: Widgets for RF inputs written in Qt for Python (PySide2).
Home-page: https://github.com/Terrabits/qtrf
Author: Nick Lalic
Author-email: nick.lalic@gmail.com
License: UNKNOWN
Project-URL: Bug Reports, https://github.com/Terrabits/qtrf/issues
Project-URL: Source, https://github.com/Terrabits/qtrf
Keywords: Qt PySide PySide2 RF Rohde Schwarz Test Measurement
Platform: UNKNOWN
Classifier: Development Status :: 4 - Beta
Classifier: Intended Audience :: Developers
Classifier: Topic :: Software Development :: Build Tools
Classifier: License :: Other/Proprietary License
Classifier: Programming Language :: Python :: 3
Classifier: Programming Language :: Python :: 3.0
Classifier: Programming Language :: Python :: 3.1
Classifier: Programming Language :: Python :: 3.2
Classifier: Programming Language :: Python :: 3.3
Classifier: Programming Language :: Python :: 3.4
Classifier: Programming Language :: Python :: 3.5
Classifier: Programming Language :: Python :: 3.6
Classifier: Programming Language :: Python :: 3.7
Requires-Python: >=3, <4
Requires-Dist: PySide2
Provides-Extra: dev
Requires-Dist: ddt ; extra == 'dev'
Provides-Extra: test
Requires-Dist: ddt ; extra == 'test'
